jupyturtle/__init__.py
jupyturtle/jupyturtle.py
jupyturtle-2024.4.1.dist-info/METADATA
jupyturtle-2024.4.1.dist-info/WHEEL
jupyturtle-2024.4.1.dist-info/licenses/LICENSE
jupyturtle-2024.4.1.dist-info/RECORD
