Metadata-Version: 2.3
Name: jupyturtle
Version: 2024.4.1
Summary: Turtle graphics for Jupyter Notebooks
Project-URL: Homepage, https://github.com/ramalho/jupyturtle
Project-URL: Issues, https://github.com/ramalho/jupyturtle/issues
Author-email: Luciano Ramalho <luciano@ramalho.org>
License-File: LICENSE
Classifier: License :: OSI Approved :: BSD License
Classifier: Operating System :: OS Independent
Classifier: Programming Language :: Python :: 3
Requires-Python: >=3.10
Requires-Dist: ipython>=8
Requires-Dist: jupyter
Requires-Dist: pytest
